techo/__init__.py
techo/__version__.py
techo/cli.py
techo/message.py
techo-0.1.0.dist-info/LICENSE
techo-0.1.0.dist-info/METADATA
techo-0.1.0.dist-info/WHEEL
techo-0.1.0.dist-info/entry_points.txt
techo-0.1.0.dist-info/top_level.txt
techo-0.1.0.dist-info/RECORD
